task_substitution/__init__.py
task_substitution/_nbdev.py
task_substitution/core.py
task_substitution/data.py
task_substitution/external_data.py
task_substitution/feature_selection.py
task_substitution/local_feature_importance.py
task_substitution/model.py
task_substitution/recover_missing.py
task_substitution/train_test_similarity.py
task_substitution-0.0.3.dist-info/LICENSE
task_substitution-0.0.3.dist-info/METADATA
task_substitution-0.0.3.dist-info/WHEEL
task_substitution-0.0.3.dist-info/entry_points.txt
task_substitution-0.0.3.dist-info/top_level.txt
task_substitution-0.0.3.dist-info/RECORD
