Metadata-Version: 2.1
Name: task-substitution
Version: 0.0.3
Summary: Solve a different task which could help solve the main task
Home-page: https://github.com/abhishek/task_substitution
Author: Abhishek Sharma
Author-email: numb3r303@gmail.com
License: Apache Software License 2.0
Keywords: ML
Platform: UNKNOWN
Classifier: Development Status :: 3 - Alpha
Classifier: Intended Audience :: Developers
Classifier: License :: OSI Approved :: Apache Software License
Classifier: Natural Language :: English
Classifier: Programming Language :: Python :: 3.6
Classifier: Programming Language :: Python :: 3.7
Classifier: Programming Language :: Python :: 3.8
Requires-Python: >=3.6
Requires-Dist: cycler (==0.10.0)
Requires-Dist: joblib (==0.14.1)
Requires-Dist: kiwisolver (==1.2.0)
Requires-Dist: lightgbm (==2.3.1)
Requires-Dist: matplotlib (==3.2.1)
Requires-Dist: numpy (==1.18.2)
Requires-Dist: pandas (==1.0.3)
Requires-Dist: pyparsing (==2.4.7)
Requires-Dist: python-dateutil (==2.8.1)
Requires-Dist: scikit-learn (==0.22.2.post1)
Requires-Dist: scipy (==1.4.1)
Requires-Dist: six (==1.14.0)
Requires-Dist: xgboost (==1.0.2)
